{
  "id": "pe4BfKmVPa",
  "data": {
    "content": {
      "type": "doc",
      "content": [
        {
          "type": "heading",
          "attrs": {
            "level": 3,
            "textAlign": "start"
          },
          "content": [
            {
              "text": "Content card container",
              "type": "text",
              "marks": [
                {
                  "type": "bold"
                }
              ]
            }
          ]
        },
        {
          "type": "paragraph",
          "attrs": {
            "textAlign": "start"
          },
          "content": [
            {
              "text": "This is the default style for a card container. You can use this on any type of information you feel can be grouped.",
              "type": "text"
            }
          ]
        }
      ]
    }
  },
  "size": null,
  "blockType": "text-editor"
}
